bman/__init__.py
bman/main.py
bman-0.9.dist-info/LICENSE.md
bman-0.9.dist-info/METADATA
bman-0.9.dist-info/WHEEL
bman-0.9.dist-info/entry_points.txt
bman-0.9.dist-info/top_level.txt
bman-0.9.dist-info/RECORD
