Metadata-Version: 2.1
Name: bman
Version: 0.9
Summary: Your command line bookmark manager.
Home-page: https://github.com/luismedel/bman
Author: Luis Medel
Author-email: luis@luismedel.com
Keywords: bookmarks
Classifier: Development Status :: 4 - Beta
Classifier: Environment :: Console
Classifier: Intended Audience :: Developers
Classifier: Intended Audience :: End Users/Desktop
Classifier: Operating System :: Unix
Classifier: Topic :: Internet
Classifier: Topic :: Database
Classifier: Topic :: Internet :: WWW/HTTP
Classifier: Programming Language :: Python :: 3
Classifier: License :: OSI Approved :: GNU Affero General Public License v3 or later (AGPLv3+)
License-File: LICENSE.md
Requires-Dist: click
Requires-Dist: orjson
